markupever-0.3.1.dist-info/METADATA
markupever-0.3.1.dist-info/WHEEL
markupever-0.3.1.dist-info/licenses/LICENSE
markupever.libs/libgcc_s-5b5488a6.so.1
markupever/__init__.py
markupever/_display.py
markupever/_rustlib.pyi
markupever/_rustlib.pypy39-pp73-arm-linux-gnu.so
markupever/dom.py
markupever/iterators.py
markupever/parser.py
markupever/py.typed
markupever-0.3.1.dist-info/RECORD
